gcs_basic/__init__.py
gcs_basic/gcs.py
gcs_basic-2.0.1.dist-info/LICENSE
gcs_basic-2.0.1.dist-info/METADATA
gcs_basic-2.0.1.dist-info/WHEEL
gcs_basic-2.0.1.dist-info/top_level.txt
gcs_basic-2.0.1.dist-info/RECORD
