Metadata-Version: 2.1
Name: gcs-basic
Version: 2.0.1
Summary: Gcs simple functions
Home-page: UNKNOWN
Author: antonio
Author-email: antonio258p@gmail.com
License: UNKNOWN
Platform: UNKNOWN
Requires-Python: >=3.6
License-File: LICENSE
